synthetic_control/__init__.py
synthetic_control/model.py
synthetic_control/analysis/__init__.py
synthetic_control/analysis/compare.py
tests/__init__.py
tests/test_model.py
tests/analysis/__init__.py
tests/analysis/test_compare.py
synthetic_control-0.0.5.dist-info/METADATA
synthetic_control-0.0.5.dist-info/WHEEL
synthetic_control-0.0.5.dist-info/top_level.txt
synthetic_control-0.0.5.dist-info/RECORD
